supermaker_ai_image_master_2/__init__.py
supermaker_ai_image_master_2-1766750.238.33.dist-info/licenses/LICENSE
supermaker_ai_image_master_2-1766750.238.33.dist-info/METADATA
supermaker_ai_image_master_2-1766750.238.33.dist-info/WHEEL
supermaker_ai_image_master_2-1766750.238.33.dist-info/top_level.txt
supermaker_ai_image_master_2-1766750.238.33.dist-info/RECORD
